Metadata-Version: 2.1
Name: name-sanitizer
Version: 1.0.0
Summary: Python script for sanitize files and directories names
Home-page: https://github.com/xcesaralejandro/name_sanitizer
Author: César Alejandro Mora Cid
Author-email: cesar.mcid@gmail.com
License: MIT
Download-URL: https://github.com/xcesaralejandro/name_sanitizer
Keywords: name,sanitizer,directories,files
Platform: UNKNOWN
Classifier: Programming Language :: Python :: 3
Requires-Python: >=3.0
